[
  {
    "plan": {
      "analysis": {
        "description": "*",
        "blocked": false,
        "help": false
      }
    }
  },
  {
    "design": {
      "workflow": {
        "description": "**",
        "blocked": true,
        "help": false
      }
    }
  },
  {
    "devops": {
      "security": {
        "description": "***",
        "blocked": false,
        "help": true
      }
    }
  },
  {
    "develop": {
      "implementation": {
        "description": "**",
        "blocked": true,
        "help": true
      }
    }
  },
  {
    "test": {
      "automation": {
        "description": "*",
        "blocked": false,
        "help": false
      }
    }
  }
]